[{"id": 3, "qtd": 5, "preco": 54.0, "id_venda": 1, "id_produto": 2}, {"id": 4, "qtd": 5, "preco": 54.0, "id_venda": 1, "id_produto": 2}, {"id": 6, "qtd": 5, "preco": 54.0, "id_venda": 2, "id_produto": 2}, {"id": 7, "qtd": 5, "preco": 54.0, "id_venda": 2, "id_produto": 2}, {"id": 9, "qtd": 5, "preco": 54.0, "id_venda": 3, "id_produto": 2}, {"id": 11, "qtd": 5, "preco": 54.0, "id_venda": 4, "id_produto": 2}, {"id": 12, "qtd": 5, "preco": 54.0, "id_venda": 4, "id_produto": 2}, {"id": 14, "qtd": 7, "preco": 24.0, "id_venda": 6, "id_produto": 1}, {"id": 16, "qtd": 7, "preco": 24.0, "id_venda": 8, "id_produto": 1}, {"id": 18, "qtd": 13, "preco": 54.0, "id_venda": 11, "id_produto": 2}, {"id": 20, "qtd": 13, "preco": 54.0, "id_venda": 13, "id_produto": 2}, {"id": 22, "qtd": 1, "preco": 24.0, "id_venda": 15, "id_produto": 1}, {"id": 24, "qtd": 2, "preco": 24.0, "id_venda": 16, "id_produto": 1}, {"id": 26, "qtd": 3, "preco": 54.0, "id_venda": 18, "id_produto": 2}, {"id": 28, "qtd": 4, "preco": 24.0, "id_venda": 21, "id_produto": 1}, {"id": 30, "qtd": 4, "preco": 24.0, "id_venda": 23, "id_produto": 1}, {"id": 32, "qtd": 4, "preco": 24.0, "id_venda": 25, "id_produto": 1}, {"id": 34, "qtd": 4, "preco": 24.0, "id_venda": 27, "id_produto": 1}, {"id": 36, "qtd": 7, "preco": 24.0, "id_venda": 29, "id_produto": 1}, {"id": 38, "qtd": 8, "preco": 54.0, "id_venda": 31, "id_produto": 2}, {"id": 40, "qtd": 8, "preco": 54.0, "id_venda": 33, "id_produto": 2}, {"id": 42, "qtd": 6, "preco": 54.0, "id_venda": 35, "id_produto": 2}, {"id": 44, "qtd": 6, "preco": 54.0, "id_venda": 37, "id_produto": 2}, {"id": 46, "qtd": 7, "preco": 24.0, "id_venda": 39, "id_produto": 1}, {"id": 48, "qtd": 7, "preco": 24.0, "id_venda": 41, "id_produto": 1}, {"id": 49, "qtd": 5, "preco": 54.0, "id_venda": 42, "id_produto": 2}, {"id": 51, "qtd": 5, "preco": 54.0, "id_venda": 43, "id_produto": 2}, {"id": 53, "qtd": 5, "preco": 54.0, "id_venda": 44, "id_produto": 2}, {"id": 55, "qtd": 5, "preco": 54.0, "id_venda": 46, "id_produto": 2}, {"id": 56, "qtd": 5, "preco": 54.0, "id_venda": 47, "id_produto": 2}, {"id": 58, "qtd": 5, "preco": 54.0, "id_venda": 48, "id_produto": 2}, {"id": 60, "qtd": 5, "preco": 54.0, "id_venda": 49, "id_produto": 2}, {"id": 61, "qtd": 5, "preco": 54.0, "id_venda": 50, "id_produto": 2}, {"id": 63, "qtd": 5, "preco": 54.0, "id_venda": 51, "id_produto": 2}, {"id": 65, "qtd": 5, "preco": 54.0, "id_venda": 52, "id_produto": 2}, {"id": 67, "qtd": 5, "preco": 54.0, "id_venda": 54, "id_produto": 2}, {"id": 69, "qtd": 7, "preco": 24.0, "id_venda": 56, "id_produto": 1}, {"id": 71, "qtd": 7, "preco": 24.0, "id_venda": 58, "id_produto": 1}, {"id": 73, "qtd": 7, "preco": 24.0, "id_venda": 60, "id_produto": 1}, {"id": 75, "qtd": 2, "preco": 24.0, "id_venda": 62, "id_produto": 1}, {"id": 77, "qtd": 2, "preco": 24.0, "id_venda": 64, "id_produto": 1}]